CHANGELOG.rst
CONTRIBUTORS.rst
LICENSE.txt
MANIFEST.in
README.rst
logrep
logrep.bat
logrep.py
setup.py
wtop
wtop.bat
wtop.cfg
wtop.egg-info/PKG-INFO
wtop.egg-info/SOURCES.txt
wtop.egg-info/dependency_links.txt
wtop.egg-info/requires.txt
wtop.egg-info/top_level.txt