Metadata-Version: 1.0
Name: wtop
Version: 0.7.7
Summary: 'top' for Apache and other web servers, plus powerful loggrepping
Home-page: https://github.com/ClockworkNet/wtop
Author: Timid Robot Zehta
Author-email: tim@clockwork.net
License: BSD 3-Clause License
Download-URL: https://github.com/ClockworkNet/wtop/releases
Platform: UNKNOWN
Classifier: Environment :: Console
Classifier: Intended Audience :: System Administrators
Classifier: License :: OSI Approved :: BSD License
Classifier: Topic :: System :: Logging
Classifier: Topic :: Utilities
